credos/__init__.py
credos-0.0.1.dist-info/METADATA
credos-0.0.1.dist-info/WHEEL
credos-0.0.1.dist-info/RECORD
