Metadata-Version: 2.3
Name: credos
Version: 0.0.1
Summary: Conflict-free Replicated Document Store
Project-URL: Homepage, https://github.com/k98kurz/credos-python
Project-URL: Bug Tracker, https://github.com/k98kurz/credos-python/issues
Author-email: k98kurz <k98kurz@gmail.com>
Classifier: Development Status :: 2 - Pre-Alpha
Classifier: License :: OSI Approved :: ISC License (ISCL)
Classifier: Operating System :: OS Independent
Classifier: Programming Language :: Python :: 3
Classifier: Topic :: Database
Requires-Python: >=3.10
Requires-Dist: packify>=0.2.2
Requires-Dist: sqloquent>=0.3.4
Requires-Dist: tapescript>=0.4.1
